dataria/CHRON.py
dataria/DATA.py
dataria/GEO.py
dataria/MATH.py
dataria/__init__.py
dataria-0.4.2.dist-info/licenses/LICENSE
docs/conf.py
dataria-0.4.2.dist-info/METADATA
dataria-0.4.2.dist-info/WHEEL
dataria-0.4.2.dist-info/top_level.txt
dataria-0.4.2.dist-info/RECORD
