Metadata-Version: 2.4
Name: dataria
Version: 0.4.2
Summary: DATAria utils
Author: Christoph Sander
Requires-Python: >=3.6
License-File: LICENSE
Requires-Dist: SPARQLWrapper
Requires-Dist: geopandas
Requires-Dist: shapely
Requires-Dist: folium
Requires-Dist: matplotlib
Requires-Dist: mapclassify
Requires-Dist: plotly
Requires-Dist: seaborn
Requires-Dist: pandas
Requires-Dist: upsetplot
Requires-Dist: rapidfuzz
Dynamic: license-file
